coopscenes/__init__.py
coopscenes/core.py
coopscenes/data/__init__.py
coopscenes/data/agent.py
coopscenes/data/data.py
coopscenes/data/frame.py
coopscenes/data/metadata.py
coopscenes/data/sensors.py
coopscenes/develop/__init__.py
coopscenes/develop/tests.py
coopscenes/develop/visualisation.py
coopscenes/miscellaneous/__init__.py
coopscenes/miscellaneous/error_exceptions.py
coopscenes/miscellaneous/helper.py
coopscenes/miscellaneous/variables.py
coopscenes/utils/__init__.py
coopscenes/utils/fusion.py
coopscenes/utils/image.py
coopscenes/utils/managing.py
coopscenes/utils/transformation.py
coopscenes/utils/visualisation.py
CoopScenes-1.2.4.dist-info/LICENSE
CoopScenes-1.2.4.dist-info/METADATA
CoopScenes-1.2.4.dist-info/WHEEL
CoopScenes-1.2.4.dist-info/top_level.txt
CoopScenes-1.2.4.dist-info/RECORD
