Metadata-Version: 2.1
Name: CoopScenes
Version: 1.2.4
Summary: Dev-Kit for CoopScenes
Home-page: https://github.com/MarcelVSHNS/coopscenes.git
Author: Marcel und Alex
Author-email: marcel.vosshans@hs-esslingen.de
License: Apache License 2.0
Requires-Python: >=3.7
License-File: LICENSE
Requires-Dist: numpy
Requires-Dist: Pillow
Requires-Dist: dill
Requires-Dist: scipy
Requires-Dist: opencv-python
Requires-Dist: matplotlib
Requires-Dist: zstandard
Requires-Dist: pytz
Requires-Dist: kiss-icp==1.2.0
